mol2chemfigPy3/__init__.py
mol2chemfigPy3/__main__.py
mol2chemfigPy3/atom.py
mol2chemfigPy3/bond.py
mol2chemfigPy3/chemfig_mappings.py
mol2chemfigPy3/common.py
mol2chemfigPy3/main.py
mol2chemfigPy3/molecule.py
mol2chemfigPy3/optionparser.py
mol2chemfigPy3/options.py
mol2chemfigPy3/processor.py
mol2chemfigpy3-1.5.14.dist-info/licenses/LICENSE
mol2chemfigpy3-1.5.14.dist-info/METADATA
mol2chemfigpy3-1.5.14.dist-info/WHEEL
mol2chemfigpy3-1.5.14.dist-info/entry_points.txt
mol2chemfigpy3-1.5.14.dist-info/top_level.txt
mol2chemfigpy3-1.5.14.dist-info/RECORD
