Metadata-Version: 2.4
Name: mol2chemfigPy3
Version: 1.5.14
Summary: python3 version of mol2chemfig
Home-page: https://augus1999.github.io/mol2chemfigPy3/
Author: Nianze A. Tao
Author-email: tao-nianze@hiroshima-u.ac.jp
License: MIT
Project-URL: Source, https://github.com/Augus1999/mol2chemfigPy3
Keywords: Chemistry,chemfig
Classifier: Development Status :: 5 - Production/Stable
Classifier: Environment :: Console
Classifier: Intended Audience :: Science/Research
Classifier: Natural Language :: English
Classifier: Programming Language :: Python :: 3
Classifier: Topic :: Scientific/Engineering :: Chemistry
Requires-Python: >=3.7
License-File: LICENSE
Requires-Dist: epam.indigo
Requires-Dist: colorama; platform_system == "Windows"
Dynamic: author
Dynamic: author-email
Dynamic: classifier
Dynamic: description
Dynamic: description-content-type
Dynamic: home-page
Dynamic: keywords
Dynamic: license
Dynamic: license-file
Dynamic: project-url
Dynamic: requires-dist
Dynamic: requires-python
Dynamic: summary
